README.txt
setup.py
docs/LICENSE.GPL
docs/LICENSE.txt
plonehrm/__init__.py
plonehrm.absence.egg-info/PKG-INFO
plonehrm.absence.egg-info/SOURCES.txt
plonehrm.absence.egg-info/dependency_links.txt
plonehrm.absence.egg-info/entry_points.txt
plonehrm.absence.egg-info/namespace_packages.txt
plonehrm.absence.egg-info/not-zip-safe
plonehrm.absence.egg-info/requires.txt
plonehrm.absence.egg-info/top_level.txt
plonehrm/absence/HISTORY.txt
plonehrm/absence/README.txt
plonehrm/absence/TODO.txt
plonehrm/absence/__init__.py
plonehrm/absence/absence.py
plonehrm/absence/config.py
plonehrm/absence/configure.zcml
plonehrm/absence/deprecation.zcml
plonehrm/absence/events.py
plonehrm/absence/flags.py
plonehrm/absence/interfaces.py
plonehrm/absence/permissions.zcml
plonehrm/absence/rebuild_i18n.sh
plonehrm/absence/setuphandlers.py
plonehrm/absence/tool.gif
plonehrm/absence/tool.py
plonehrm/absence/utils.py
plonehrm/absence/validators.py
plonehrm/absence/browser/__init__.py
plonehrm/absence/browser/absence.kss
plonehrm/absence/browser/absence.py
plonehrm/absence/browser/absence_view.pt
plonehrm/absence/browser/absence_viewlet.pt
plonehrm/absence/browser/absencelist.pt
plonehrm/absence/browser/configure.zcml
plonehrm/absence/browser/improvement_edit.pt
plonehrm/absence/browser/improvement_view.pt
plonehrm/absence/browser/interview.pt
plonehrm/absence/content/__init__.py
plonehrm/absence/content/absence.py
plonehrm/absence/content/configure.zcml
plonehrm/absence/content/evaluationInterview.py
plonehrm/absence/content/file.py
plonehrm/absence/content/note.py
plonehrm/absence/docs/absence.txt
plonehrm/absence/docs/checker.txt
plonehrm/absence/locales/absence.pot
plonehrm/absence/locales/nl/LC_MESSAGES/absence.po
plonehrm/absence/notifications/__init__.py
plonehrm/absence/notifications/absence6weekrepeatemail.pt
plonehrm/absence/notifications/absenceweek1email.pt
plonehrm/absence/notifications/absenceweek6email.pt
plonehrm/absence/notifications/absenceweek8email.pt
plonehrm/absence/notifications/checkers.py
plonehrm/absence/notifications/configure.zcml
plonehrm/absence/notifications/events.py
plonehrm/absence/notifications/interfaces.py
plonehrm/absence/profiles/default/actionicons.xml
plonehrm/absence/profiles/default/catalog.xml
plonehrm/absence/profiles/default/controlpanel.xml
