Metadata-Version: 1.0
Name: plonehrm.absence
Version: 1.4.3
Summary: Register employee absence
Home-page: UNKNOWN
Author: Zest Software
Author-email: info@zestsoftware.nl
License: GPL
Platform: UNKNOWN
Classifier: Framework :: Plone
Classifier: Programming Language :: Python
Classifier: Topic :: Software Development :: Libraries :: Python Modules
